task1/rom.sv
module rom #(
    parameter   ADDRESS_WIDTH = 8,
                DATA_WIDTH = 8
)(
    input logic                     clk,
    input logic [ADDRESS_WIDTH-1:0] addr,
    output logic [DATA_WIDTH-1:0]    dout
);

logic [DATA_WIDTH-1:0] rom_array [2**ADDRESS_WIDTH-1:0];

initial begin
    $display("Loading rom.");
    $readmemh("sinerom.mem", rom_array);
end

always_ff @(posedge clk)
    //output is synchronous
    dout <= rom_array [addr];

endmodule

task1/counter.sv
module counter #(
    parameter WIDTH = 8
)(
    //interface signals
    input logic     clk,            //clock
    input logic     rst,            //reset
    input logic     en,             //counter enable
    input logic     incr,
    output logic [WIDTH-1:0] count  //count output
);

always_ff @ (posedge clk)
  if(rst) count <= {WIDTH{1'b0}};
  else if(en) count <= count + incr;
  // if enable true than increase count by incr
  else count <= count;
  //reincluded enable using if statement

endmodule

task1/sinegen.sv
module sinegen #(
    parameter   A_WIDTH = 8,
                D_WIDTH = 8
)(
    //INTERFACE SIGNALS
    input logic                 clk, //clock
    input logic                 rst, //reset
    input logic                 en,  //enable
    input logic [D_WIDTH-1:0]   incr,//increment for addr counter
    output logic [D_WIDTH-1:0]  dout //output data
);

    logic [A_WIDTH-1:0]         address; //interconnect wire

counter addrCounter(
    .clk (clk),
    .rst (rst),
    .en (en),
    .incr (incr),
    .count (address)
);

rom sineRom(
    .clk  (clk),
    .addr (address),
    .dout (dout)
);

endmodule

task1/sinegen.vcd
$version Generated by VerilatedVcd $end
$date Thu Oct 24 10:50:19 2024 $end
$timescale 1ps $end

 $scope module TOP $end
  $var wire  1 # clk $end
  $var wire  8 ' dout [7:0] $end
  $var wire  1 % en $end
  $var wire  8 & incr [7:0] $end
  $var wire  1 $ rst $end
  $scope module sinegen $end
   $var wire 32 * A_WIDTH [31:0] $end
   $var wire 32 * D_WIDTH [31:0] $end
   $var wire  8 ( address [7:0] $end
   $var wire  1 # clk $end
   $var wire  8 ' dout [7:0] $end
   $var wire  1 % en $end
   $var wire  8 & incr [7:0] $end
   $var wire  1 $ rst $end
   $scope module addrCounter $end
    $var wire 32 * WIDTH [31:0] $end
    $var wire  1 # clk $end
    $var wire  8 ( count [7:0] $end
    $var wire  1 % en $end
    $var wire  1 ) incr $end
    $var wire  1 $ rst $end
   $upscope $end
   $scope module sineRom $end
    $var wire 32 * ADDRESS_WIDTH [31:0] $end
    $var wire 32 * DATA_WIDTH [31:0] $end
    $var wire  8 ( addr [7:0] $end
    $var wire  1 # clk $end
    $var wire  8 ' dout [7:0] $end
   $upscope $end
  $upscope $end
 $upscope $end
$enddefinitions $end


#0
1#
0$
1%
b00000001 &
b00000000 '
b00000000 (
1)
b00000000000000000000000000001000 *
#1
0#
#2
1#
b01100010 &
b11111110 '
b00000001 (
0)
#3
0#
#4
1#
b11111101 '
#5
0#
#6
1#
#7
0#
#8
1#
#9
0#
#10
1#
#11
0#
#12
1#
#13
0#
#14
1#
#15
0#
#16
1#
#17
0#
#18
1#
#19
0#
#20
1#
#21
0#
#22
1#
#23
0#
#24
1#
#25
0#
#26
1#
#27
0#
#28
1#
#29
0#
#30
1#
#31
0#
#32
1#
#33
0#
#34
1#
#35
0#
#36
1#
#37
0#
#38
1#
#39
0#
#40
1#
#41
0#
#42
1#
#43
0#
#44
1#
#45
0#
#46
1#
#47
0#
#48
1#
#49
0#
#50
1#
#51
0#
#52
1#
#53
0#
#54
1#
#55
0#
#56
1#
#57
0#
#58
1#
#59
0#
#60
1#
#61
0#
#62
1#
#63
0#
#64
1#
#65
0#
#66
1#
#67
0#
#68
1#
#69
0#
#70
1#
#71
0#
#72
1#
#73
0#
#74
1#
#75
0#
#76
1#
#77
0#
#78
1#
#79
0#
#80
1#
#81
0#
#82
1#
#83
0#
#84
1#
#85
0#
#86
1#
#87
0#
#88
1#
#89
0#
#90
1#
#91
0#
#92
1#
#93
0#
#94
1#
#95
0#
#96
1#
#97
0#
#98
1#
#99
0#
#100
1#
#101
0#
#102
1#
#103
0#
#104
1#
#105
0#
#106
1#
#107
0#
#108
1#
#109
0#
#110
1#
#111
0#
#112
1#
#113
0#
#114
1#
#115
0#
#116
1#
#117
0#
#118
1#
#119
0#
#120
1#
#121
0#
#122
1#
#123
0#
#124
1#
#125
0#
#126
1#
#127
0#
#128
1#
#129
0#
#130
1#
#131
0#
#132
1#
#133
0#
#134
1#
#135
0#
#136
1#
#137
0#
#138
1#
#139
0#
#140
1#
#141
0#
#142
1#
#143
0#
#144
1#
#145
0#
#146
1#
#147
0#
#148
1#
#149
0#
#150
1#
#151
0#
#152
1#
#153
0#
#154
1#
#155
0#
#156
1#
#157
0#
#158
1#
#159
0#
#160
1#
#161
0#
#162
1#
#163
0#
#164
1#
#165
0#
#166
1#
#167
0#
#168
1#
#169
0#
#170
1#
#171
0#
#172
1#
#173
0#
#174
1#
#175
0#
#176
1#
#177
0#
#178
1#
#179
0#
#180
1#
#181
0#
#182
1#
#183
0#
#184
1#
#185
0#
#186
1#
#187
0#
#188
1#
#189
0#
#190
1#
#191
0#
#192
1#
#193
0#
#194
1#
#195
0#
#196
1#
#197
0#
#198
1#
#199
0#
#200
1#
#201
0#
#202
1#
#203
0#
#204
1#
#205
0#
#206
1#
#207
0#
#208
1#
#209
0#
#210
1#
#211
0#
#212
1#
#213
0#
#214
1#
#215
0#
#216
1#
#217
0#
#218
1#
#219
0#
#220
1#
#221
0#
#222
1#
#223
0#
#224
1#
#225
0#
#226
1#
#227
0#
#228
1#
#229
0#
#230
1#
#231
0#
#232
1#
#233
0#
#234
1#
#235
0#
#236
1#
#237
0#
#238
1#
#239
0#
#240
1#
#241
0#
#242
1#
#243
0#
#244
1#
#245
0#
#246
1#
#247
0#
#248
1#
#249
0#
#250
1#
#251
0#
#252
1#
#253
0#
#254
1#
#255
0#
#256
1#
#257
0#
#258
1#
#259
0#
#260
1#
#261
0#
#262
1#
#263
0#
#264
1#
#265
0#
#266
1#
#267
0#
#268
1#
#269
0#
#270
1#
#271
0#
#272
1#
#273
0#
#274
1#
#275
0#
#276
1#
#277
0#
#278
1#
#279
0#
#280
1#
#281
0#
#282
1#
#283
0#
#284
1#
#285
0#
#286
1#
#287
0#
#288
1#
#289
0#
#290
1#
#291
0#
#292
1#
#293
0#
#294
1#
#295
0#
#296
1#
#297
0#
#298
1#
#299
0#
#300
1#
#301
0#
#302
1#
#303
0#
#304
1#
#305
0#
#306
1#
#307
0#
#308
1#
#309
0#
#310
1#
#311
0#
#312
1#
#313
0#
#314
1#
#315
0#
#316
1#
#317
0#
#318
1#
#319
0#
#320
1#
b01100001 &
1)
#321
0#
#322
1#
b00000010 (
#323
0#
#324
1#
b00000011 (
#325
0#
#326
1#
b00000100 (
#327
0#
#328
1#
b00000101 (
#329
0#
#330
1#
b00000110 (
#331
0#
#332
1#
b11111100 '
b00000111 (
#333
0#
#334
1#
b00001000 (
#335
0#
#336
1#
b11111011 '
b00001001 (
#337
0#
#338
1#
b01100000 &
b11111010 '
b00001010 (
0)
#339
0#
#340
1#
#341
0#
#342
1#
#343
0#
#344
1#
#345
0#
#346
1#
#347
0#
#348
1#
#349
0#
#350
1#
#351
0#
#352
1#
#353
0#
#354
1#
#355
0#
#356
1#
#357
0#
#358
1#
#359
0#
#360
1#
#361
0#
#362
1#
b01011111 &
1)
#363
0#
#364
1#
b00001011 (
#365
0#
#366
1#
b11111001 '
b00001100 (
#367
0#
#368
1#
b11111000 '
b00001101 (
#369
0#
#370
1#
b11110111 '
b00001110 (
#371
0#
#372
1#
b11110110 '
b00001111 (
#373
0#
#374
1#
b11110101 '
b00010000 (
#375
0#
#376
1#
b11110100 '
b00010001 (
#377
0#
#378
1#
b11110011 '
b00010010 (
#379
0#
#380
1#
b11110001 '
b00010011 (
#381
0#
#382
1#
b11110000 '
b00010100 (
#383
0#
#384
1#
b11101111 '
b00010101 (
#385
0#
#386
1#
b11101101 '
b00010110 (
#387
0#
#388
1#
b11101011 '
b00010111 (
#389
0#
#390
1#
b11101010 '
b00011000 (
#391
0#
#392
1#
b11101000 '
b00011001 (
#393
0#
#394
1#
b11100110 '
b00011010 (
#395
0#
#396
1#
b11100101 '
b00011011 (
#397
0#
#398
1#
b11100011 '
b00011100 (
#399
0#
#400
1#
b11100001 '
b00011101 (
#401
0#
#402
1#
b11011111 '
b00011110 (
#403
0#
#404
1#
b11011101 '
b00011111 (
#405
0#
#406
1#
b11011010 '
b00100000 (
#407
0#
#408
1#
b11011000 '
b00100001 (
#409
0#
#410
1#
b11010110 '
b00100010 (
#411
0#
#412
1#
b11010100 '
b00100011 (
#413
0#
#414
1#
b11010001 '
b00100100 (
#415
0#
#416
1#
b11001111 '
b00100101 (
#417
0#
#418
1#
b11001101 '
b00100110 (
#419
0#
#420
1#
b11001010 '
b00100111 (
#421
0#
#422
1#
b11001000 '
b00101000 (
#423
0#
#424
1#
b11000101 '
b00101001 (
#425
0#
#426
1#
b11000010 '
b00101010 (
#427
0#
#428
1#
b11000000 '
b00101011 (
#429
0#
#430
1#
b10111101 '
b00101100 (
#431
0#
#432
1#
b10111010 '
b00101101 (
#433
0#
#434
1#
b10111000 '
b00101110 (
#435
0#
#436
1#
b10110101 '
b00101111 (
#437
0#
#438
1#
b10110010 '
b00110000 (
#439
0#
#440
1#
b10101111 '
b00110001 (
#441
0#
#442
1#
b10101100 '
b00110010 (
#443
0#
#444
1#
b10101001 '
b00110011 (
#445
0#
#446
1#
b10100110 '
b00110100 (
#447
0#
#448
1#
b10100011 '
b00110101 (
#449
0#
#450
1#
b10100000 '
b00110110 (
#451
0#
#452
1#
b10011101 '
b00110111 (
#453
0#
#454
1#
b10011010 '
b00111000 (
#455
0#
#456
1#
b10010111 '
b00111001 (
#457
0#
#458
1#
b10010100 '
b00111010 (
#459
0#
#460
1#
b10010001 '
b00111011 (
#461
0#
#462
1#
b10001110 '
b00111100 (
#463
0#
#464
1#
b10001011 '
b00111101 (
#465
0#
#466
1#
b10001000 '
b00111110 (
#467
0#
#468
1#
b10000101 '
b00111111 (
#469
0#
#470
1#
b10000010 '
b01000000 (
#471
0#
#472
1#
b01111110 '
b01000001 (
#473
0#
#474
1#
b01111011 '
b01000010 (
#475
0#
#476
1#
b01111000 '
b01000011 (
#477
0#
#478
1#
b01110101 '
b01000100 (
#479
0#
#480
1#
b01110010 '
b01000101 (
#481
0#
#482
1#
b01101111 '
b01000110 (
#483
0#
#484
1#
b01101100 '
b01000111 (
#485
0#
#486
1#
b01101001 '
b01001000 (
#487
0#
#488
1#
b01100110 '
b01001001 (
#489
0#
#490
1#
b01100011 '
b01001010 (
#491
0#
#492
1#
b01100000 '
b01001011 (
#493
0#
#494
1#
b01011101 '
b01001100 (
#495
0#
#496
1#
b01011010 '
b01001101 (
#497
0#
#498
1#
b01010111 '
b01001110 (
#499
0#
#500
1#
b01010100 '
b01001111 (
#501
0#
#502
1#
b01010001 '
b01010000 (
#503
0#
#504
1#
b01001110 '
b01010001 (
#505
0#
#506
1#
b01001011 '
b01010010 (
#507
0#
#508
1#
b01001000 '
b01010011 (
#509
0#
#510
1#
b01000101 '
b01010100 (
#511
0#
#512
1#
b01000011 '
b01010101 (
#513
0#
#514
1#
b01000000 '
b01010110 (
#515
0#
#516
1#
b00111101 '
b01010111 (
#517
0#
#518
1#
b00111011 '
b01011000 (
#519
0#
#520
1#
b00111000 '
b01011001 (
#521
0#
#522
1#
b00110101 '
b01011010 (
#523
0#
#524
1#
b00110011 '
b01011011 (
#525
0#
#526
1#
b00110000 '
b01011100 (
#527
0#
#528
1#
b00101110 '
b01011101 (
#529
0#
#530
1#
b00101100 '
b01011110 (
#531
0#
#532
1#
b00101001 '
b01011111 (
#533
0#
#534
1#
b00100111 '
b01100000 (
#535
0#
#536
1#
b00100101 '
b01100001 (
#537
0#
#538
1#
b00100011 '
b01100010 (
#539
0#
#540
1#
b00100000 '
b01100011 (
#541
0#
#542
1#
b00011110 '
b01100100 (
#543
0#
#544
1#
b00011100 '
b01100101 (
#545
0#
#546
1#
b00011010 '
b01100110 (
#547
0#
#548
1#
b00011000 '
b01100111 (
#549
0#
#550
1#
b00010111 '
b01101000 (
#551
0#
#552
1#
b00010101 '
b01101001 (
#553
0#
#554
1#
b00010011 '
b01101010 (
#555
0#
#556
1#
b00010010 '
b01101011 (
#557
0#
#558
1#
b00010000 '
b01101100 (
#559
0#
#560
1#
b00001110 '
b01101101 (
#561
0#
#562
1#
b00001101 '
b01101110 (
#563
0#
#564
1#
b00001100 '
b01101111 (
#565
0#
#566
1#
b00001010 '
b01110000 (
#567
0#
#568
1#
b00001001 '
b01110001 (
#569
0#
#570
1#
b00001000 '
b01110010 (
#571
0#
#572
1#
b00000111 '
b01110011 (
#573
0#
#574
1#
b00000110 '
b01110100 (
#575
0#
#576
1#
b00000101 '
b01110101 (
#577
0#
#578
1#
b00000100 '
b01110110 (
#579
0#
#580
1#
b00000011 '
b01110111 (
#581
0#
#582
1#
b01111000 (
#583
0#
#584
1#
b00000010 '
b01111001 (
#585
0#
#586
1#
b00000001 '
b01111010 (
#587
0#
#588
1#
b01111011 (
#589
0#
#590
1#
b00000000 '
b01111100 (
#591
0#
#592
1#
b01111101 (
#593
0#
#594
1#
b01111110 (
#595
0#
#596
1#
b01111111 (
#597
0#
#598
1#
b10000000 (
#599
0#
#600
1#
b10000001 (
#601
0#
#602
1#
b10000010 (
#603
0#
#604
1#
b10000011 (
#605
0#
#606
1#
b10000100 (
#607
0#
#608
1#
b10000101 (
#609
0#
#610
1#
b10000110 (
#611
0#
#612
1#
b00000001 '
b10000111 (
#613
0#
#614
1#
b10001000 (
#615
0#
#616
1#
b00000010 '
b10001001 (
#617
0#
#618
1#
b00000011 '
b10001010 (
#619
0#
#620
1#
b10001011 (
#621
0#
#622
1#
b00000100 '
b10001100 (
#623
0#
#624
1#
b00000101 '
b10001101 (
#625
0#
#626
1#
b00000110 '
b10001110 (
#627
0#
#628
1#
b00000111 '
b10001111 (
#629
0#
#630
1#
b00001000 '
b10010000 (
#631
0#
#632
1#
b00001001 '
b10010001 (
#633
0#
#634
1#
b00001010 '
b10010010 (
#635
0#
#636
1#
b00001100 '
b10010011 (
#637
0#
#638
1#
b00001101 '
b10010100 (
#639
0#
#640
1#
b00001110 '
b10010101 (
#641
0#
#642
1#
b00010000 '
b10010110 (
#643
0#
#644
1#
b00010010 '
b10010111 (
#645
0#
#646
1#
b00010011 '
b10011000 (
#647
0#
#648
1#
b00010101 '
b10011001 (
#649
0#
#650
1#
b00010111 '
b10011010 (
#651
0#
#652
1#
b01100000 &
b00011000 '
b10011011 (
0)
#653
0#
#654
1#
b00011010 '
